<annotation>
  <filename>cframe_1035.jpg</filename>
  <folder>folder_1</folder>
  <object>
    <bndbox>
      <xmax>498</xmax>
      <xmin>362</xmin>
      <ymax>513</ymax>
      <ymin>366</ymin>
    </bndbox>
    <difficult>0</difficult>
    <name>person</name>
    <pose>Left</pose>
    <truncated>0</truncated>
  </object>
  <object>
    <bndbox>
      <xmax>563</xmax>
      <xmin>488</xmin>
      <ymax>462</ymax>
      <ymin>357</ymin>
    </bndbox>
    <difficult>0</difficult>
    <name>person</name>
    <pose>Left</pose>
    <truncated>0</truncated>
  </object>
  <object>
    <bndbox>
      <xmax>536</xmax>
      <xmin>460</xmin>
      <ymax>382</ymax>
      <ymin>265</ymin>
    </bndbox>
    <difficult>0</difficult>
    <name>person</name>
    <pose>Left</pose>
    <truncated>0</truncated>
  </object>
  <object>
    <bndbox>
      <xmax>480</xmax>
      <xmin>400</xmin>
      <ymax>389</ymax>
      <ymin>221</ymin>
    </bndbox>
    <difficult>0</difficult>
    <name>person</name>
    <pose>Left</pose>
    <truncated>0</truncated>
  </object>
  <object>
    <bndbox>
      <xmax>401</xmax>
      <xmin>337</xmin>
      <ymax>137</ymax>
      <ymin>27</ymin>
    </bndbox>
    <difficult>0</difficult>
    <name>person</name>
    <pose>Left</pose>
    <truncated>0</truncated>
  </object>
  <size>
    <depth>3</depth>
    <height>720</height>
    <width>1280</width>
  </size>
</annotation>