<annotation>
  <filename>cframe_1109.jpg</filename>
  <folder>folder_1</folder>
  <object>
    <bndbox>
      <xmax>401</xmax>
      <xmin>236</xmin>
      <ymax>720</ymax>
      <ymin>622</ymin>
    </bndbox>
    <difficult>0</difficult>
    <name>person</name>
    <pose>Left</pose>
    <truncated>0</truncated>
  </object>
  <object>
    <bndbox>
      <xmax>505</xmax>
      <xmin>393</xmin>
      <ymax>584</ymax>
      <ymin>416</ymin>
    </bndbox>
    <difficult>0</difficult>
    <name>person</name>
    <pose>Left</pose>
    <truncated>0</truncated>
  </object>
  <object>
    <bndbox>
      <xmax>589</xmax>
      <xmin>501</xmin>
      <ymax>556</ymax>
      <ymin>434</ymin>
    </bndbox>
    <difficult>0</difficult>
    <name>person</name>
    <pose>Left</pose>
    <truncated>0</truncated>
  </object>
  <object>
    <bndbox>
      <xmax>665</xmax>
      <xmin>570</xmin>
      <ymax>656</ymax>
      <ymin>506</ymin>
    </bndbox>
    <difficult>0</difficult>
    <name>person</name>
    <pose>Left</pose>
    <truncated>0</truncated>
  </object>
  <object>
    <bndbox>
      <xmax>694</xmax>
      <xmin>615</xmin>
      <ymax>458</ymax>
      <ymin>243</ymin>
    </bndbox>
    <difficult>0</difficult>
    <name>person</name>
    <pose>Left</pose>
    <truncated>0</truncated>
  </object>
  <object>
    <bndbox>
      <xmax>780</xmax>
      <xmin>696</xmin>
      <ymax>446</ymax>
      <ymin>260</ymin>
    </bndbox>
    <difficult>0</difficult>
    <name>person</name>
    <pose>Left</pose>
    <truncated>0</truncated>
  </object>
  <size>
    <depth>3</depth>
    <height>720</height>
    <width>1280</width>
  </size>
</annotation>