<annotation>
  <filename>cframe_1771.jpg</filename>
  <folder>folder_1</folder>
  <object>
    <bndbox>
      <xmax>715</xmax>
      <xmin>619</xmin>
      <ymax>717</ymax>
      <ymin>597</ymin>
    </bndbox>
    <difficult>0</difficult>
    <name>person</name>
    <pose>Left</pose>
    <truncated>0</truncated>
  </object>
  <object>
    <bndbox>
      <xmax>764</xmax>
      <xmin>687</xmin>
      <ymax>606</ymax>
      <ymin>486</ymin>
    </bndbox>
    <difficult>0</difficult>
    <name>person</name>
    <pose>Left</pose>
    <truncated>0</truncated>
  </object>
  <object>
    <bndbox>
      <xmax>811</xmax>
      <xmin>748</xmin>
      <ymax>555</ymax>
      <ymin>458</ymin>
    </bndbox>
    <difficult>0</difficult>
    <name>person</name>
    <pose>Left</pose>
    <truncated>0</truncated>
  </object>
  <object>
    <bndbox>
      <xmax>624</xmax>
      <xmin>552</xmin>
      <ymax>504</ymax>
      <ymin>356</ymin>
    </bndbox>
    <difficult>0</difficult>
    <name>person</name>
    <pose>Left</pose>
    <truncated>0</truncated>
  </object>
  <size>
    <depth>3</depth>
    <height>720</height>
    <width>1280</width>
  </size>
</annotation>